DDSampling/DDSampling.py
DDSampling/__init__.py
DDSampling-0.1.dist-info/METADATA
DDSampling-0.1.dist-info/WHEEL
DDSampling-0.1.dist-info/top_level.txt
DDSampling-0.1.dist-info/RECORD
